simple_config_reader/__init__.py
simple_config_reader/utils/__init__.py
simple_config_reader-0.0.5.dist-info/DESCRIPTION.rst
simple_config_reader-0.0.5.dist-info/METADATA
simple_config_reader-0.0.5.dist-info/RECORD
simple_config_reader-0.0.5.dist-info/WHEEL
simple_config_reader-0.0.5.dist-info/metadata.json
simple_config_reader-0.0.5.dist-info/top_level.txt
