Metadata-Version: 2.0
Name: simple-config-reader
Version: 0.0.5
Summary: 一个简单的配置文件读取工具
Home-page: https://github.com/anjianshi/simple-config-reader
Author: anjianshi
Author-email: anjianshi@gmail.com
License: MIT
Keywords: yaml,config
Platform: any
Classifier: Intended Audience :: Developers
Classifier: License :: OSI Approved :: MIT License
Classifier: Operating System :: OS Independent
Classifier: Programming Language :: Python
Classifier: Programming Language :: Python :: 3
Classifier: Programming Language :: Python :: 3.5
Classifier: Programming Language :: Python :: 3.6
Requires-Dist: PyYAML
